Workbook

Sheet Tarification
A1: SmartGUARD — Grille tarifaire
A2: Montants en francs CFA (F CFA), hors taxes. Version 1.17 du cahier des charges, 1er octobre 2026. Chiffres en bleu : prix saisis (modifiables).
A4: 1. Licence SmartGUARD (obligatoire, une par serveur contrôlé)
A5: Élément | B5: Prix | C5: Paiement | D5: Statut
A6: Licence perpétuelle par serveur (module complet, accès de base, notification e-mail J-30, correctifs) | B6: 150000 | C6: Une fois | D6: Validé
A7: Mise à niveau vers une version majeure (50 % de la licence) | B7: =B6*0.5 -> 75000 | C7: Une fois par serveur | D7: Proposition
A8: Transfert de la licence vers un nouveau serveur | B8: 0 | C8: — | D8: Proposition
A10: 2. Abonnement au portail (par compte fournisseur)
A11: Formule | B11: Serveurs rattachés (max) | C11: Mensuel | D11: Annuel | E11: Économie annuelle | F11: Utilisateurs inclus | G11: Statut
A12: Essentiel | B12: 10 | C12: 20000 | D12: 200000 | E12: =1-D12/(C12*12) -> 0.16666667 | F12: 3 | G12: Validé
A13: Pro | B13: 50 | C13: 60000 | D13: 500000 | E13: =1-D13/(C13*12) -> 0.30555556 | F13: 10 | G13: Validé
A14: Entreprise | B14: 999999 | C14: 100000 | D14: 1000000 | E14: =1-D14/(C14*12) -> 0.16666667 | F14: 25 | G14: Validé
A15: Utilisateurs inclus : proposition. Formule Entreprise : au-delà de 50 serveurs (999 999 = sans limite).
A17: 3. Options (nécessitent l'abonnement, prix selon la formule) — proposition
A18: Option | B18: Essentiel / mois | C18: Essentiel / an | D18: Pro / mois | E18: Pro / an | F18: Entreprise / mois | G18: Entreprise / an
A19: Application mobile du fournisseur | B19: 5000 | C19: 50000 | D19: 15000 | E19: 150000 | F19: 25000 | G19: 250000
A20: Espace client (signalement, détection de panne, webhook) | B20: 10000 | C20: 100000 | D20: 25000 | E20: 250000 | F20: 40000 | G20: 400000
A21: Utilisateur supplémentaire (par utilisateur) | B21: 2000 | C21: 20000 | D21: 2000 | E21: 20000 | F21: 2000 | G21: 20000
A22: Alertes SMS et WhatsApp (version ultérieure) | B22: Selon consommation
A23: Base de calcul : mobile ≈ 25 % et espace client ≈ 50 % du prix de la formule ; environ 17 % d'économie à l'année.

Sheet Simulateur
A1: Simulateur de coût pour un fournisseur (formules annuelles)
A2: Cellules jaunes : à saisir. Les autres cellules se calculent.
A4: Nombre de serveurs (licences SmartGUARD) | B4: 10
A5: Serveurs rattachés au portail | B5: 10
A6: Abonnement au portail (Oui/Non) | B6: Oui
A7: Option application mobile (Oui/Non) | B7: Oui
A8: Option espace client (Oui/Non) | B8: Oui
A9: Utilisateurs supplémentaires | B9: 0
A11: Formule applicable | B11: =IF(B6="Non","Aucune",IF(B5<=Tarification!$B$12,"Essentiel",IF(B5<=Tarification!$B$13,"Pro","Entreprise"))) -> Essentiel
A12: Colonne de la formule (1 à 3) | B12: =IF(B11="Essentiel",1,IF(B11="Pro",2,IF(B11="Entreprise",3,0))) -> 1
A14: Poste | B14: Année 1 | C14: Années suivantes
A15: Licences SmartGUARD | B15: =B4*Tarification!$B$6 -> 1500000 | C15: =0 -> 0
A16: Abonnement annuel | B16: =IF(B12=0,0,INDEX(Tarification!$D$12:$D$14,B12)) -> 200000 | C16: =B16 -> 200000
A17: Application mobile (annuel) | B17: =IF(OR(B12=0,B7="Non"),0,INDEX(Tarification!$C$19:$G$19,B12*2-1)) -> 50000 | C17: =B17 -> 50000
A18: Espace client (annuel) | B18: =IF(OR(B12=0,B8="Non"),0,INDEX(Tarification!$C$20:$G$20,B12*2-1)) -> 100000 | C18: =B18 -> 100000
A19: Utilisateurs supplémentaires (annuel) | B19: =IF(B12=0,0,B9*Tarification!$C$21) -> 0 | C19: =B19 -> 0
A20: Total | B20: =SUM(B15:B19) -> 1850000 | C20: =SUM(C15:C19) -> 350000
A22: Hypothèse : sans abonnement, le fournisseur garde l'accès de base inclus dans la licence (une notification e-mail à J-30 par échéance).

Sheet Exemples
A1: Exemples (formules annuelles)
A3: Cas | B3: Serveurs | C3: Formule | D3: Mobile | E3: Espace client | F3: Année 1 | G3: Années suivantes
A4: Licence seule | B4: 3 | C4: Aucune | D4: Non | E4: Non | F4: =B4*Tarification!$B$6+G4 -> 450000 | G4: =IF(IF(C4="Essentiel",1,IF(C4="Pro",2,IF(C4="Entreprise",3,0)))=0,0,INDEX(Tarification!$D$12:$D$14,IF(C4="Essentiel",1,IF(C4="Pro",2,IF(C4="Entreprise",3,0))))+IF(D4="Oui",INDEX(Tarification!$C$19:$G$19,IF(C4="Essentiel",1,IF(C4="Pro",2,IF(C4="Entreprise",3,0)))*2-1),0)+IF(E4="Oui",INDEX(Tarification!$C$20:$G$20,IF(C4="Essentiel",1,IF(C4="Pro",2,IF(C4="Entreprise",3,0)))*2-1),0)) -> 0
A5: Essentiel | B5: 10 | C5: Essentiel | D5: Non | E5: Non | F5: =B5*Tarification!$B$6+G5 -> 1700000 | G5: =IF(IF(C5="Essentiel",1,IF(C5="Pro",2,IF(C5="Entreprise",3,0)))=0,0,INDEX(Tarification!$D$12:$D$14,IF(C5="Essentiel",1,IF(C5="Pro",2,IF(C5="Entreprise",3,0))))+IF(D5="Oui",INDEX(Tarification!$C$19:$G$19,IF(C5="Essentiel",1,IF(C5="Pro",2,IF(C5="Entreprise",3,0)))*2-1),0)+IF(E5="Oui",INDEX(Tarification!$C$20:$G$20,IF(C5="Essentiel",1,IF(C5="Pro",2,IF(C5="Entreprise",3,0)))*2-1),0)) -> 200000
A6: Essentiel + options | B6: 10 | C6: Essentiel | D6: Oui | E6: Oui | F6: =B6*Tarification!$B$6+G6 -> 1850000 | G6: =IF(IF(C6="Essentiel",1,IF(C6="Pro",2,IF(C6="Entreprise",3,0)))=0,0,INDEX(Tarification!$D$12:$D$14,IF(C6="Essentiel",1,IF(C6="Pro",2,IF(C6="Entreprise",3,0))))+IF(D6="Oui",INDEX(Tarification!$C$19:$G$19,IF(C6="Essentiel",1,IF(C6="Pro",2,IF(C6="Entreprise",3,0)))*2-1),0)+IF(E6="Oui",INDEX(Tarification!$C$20:$G$20,IF(C6="Essentiel",1,IF(C6="Pro",2,IF(C6="Entreprise",3,0)))*2-1),0)) -> 350000
A7: Pro | B7: 30 | C7: Pro | D7: Non | E7: Non | F7: =B7*Tarification!$B$6+G7 -> 5000000 | G7: =IF(IF(C7="Essentiel",1,IF(C7="Pro",2,IF(C7="Entreprise",3,0)))=0,0,INDEX(Tarification!$D$12:$D$14,IF(C7="Essentiel",1,IF(C7="Pro",2,IF(C7="Entreprise",3,0))))+IF(D7="Oui",INDEX(Tarification!$C$19:$G$19,IF(C7="Essentiel",1,IF(C7="Pro",2,IF(C7="Entreprise",3,0)))*2-1),0)+IF(E7="Oui",INDEX(Tarification!$C$20:$G$20,IF(C7="Essentiel",1,IF(C7="Pro",2,IF(C7="Entreprise",3,0)))*2-1),0)) -> 500000
A8: Pro + options | B8: 30 | C8: Pro | D8: Oui | E8: Oui | F8: =B8*Tarification!$B$6+G8 -> 5400000 | G8: =IF(IF(C8="Essentiel",1,IF(C8="Pro",2,IF(C8="Entreprise",3,0)))=0,0,INDEX(Tarification!$D$12:$D$14,IF(C8="Essentiel",1,IF(C8="Pro",2,IF(C8="Entreprise",3,0))))+IF(D8="Oui",INDEX(Tarification!$C$19:$G$19,IF(C8="Essentiel",1,IF(C8="Pro",2,IF(C8="Entreprise",3,0)))*2-1),0)+IF(E8="Oui",INDEX(Tarification!$C$20:$G$20,IF(C8="Essentiel",1,IF(C8="Pro",2,IF(C8="Entreprise",3,0)))*2-1),0)) -> 900000
A9: Entreprise + options | B9: 80 | C9: Entreprise | D9: Oui | E9: Oui | F9: =B9*Tarification!$B$6+G9 -> 13650000 | G9: =IF(IF(C9="Essentiel",1,IF(C9="Pro",2,IF(C9="Entreprise",3,0)))=0,0,INDEX(Tarification!$D$12:$D$14,IF(C9="Essentiel",1,IF(C9="Pro",2,IF(C9="Entreprise",3,0))))+IF(D9="Oui",INDEX(Tarification!$C$19:$G$19,IF(C9="Essentiel",1,IF(C9="Pro",2,IF(C9="Entreprise",3,0)))*2-1),0)+IF(E9="Oui",INDEX(Tarification!$C$20:$G$20,IF(C9="Essentiel",1,IF(C9="Pro",2,IF(C9="Entreprise",3,0)))*2-1),0)) -> 1650000
